gpgi/__init__.py
gpgi/_boundaries.py
gpgi/_data_types.py
gpgi/_lib.abi3.so
gpgi/_lib.pyi
gpgi/_load.py
gpgi/_spatial_data.py
gpgi/_typing.py
gpgi/py.typed
gpgi/typing.py
gpgi-2.1.0.dist-info/METADATA
gpgi-2.1.0.dist-info/WHEEL
gpgi-2.1.0.dist-info/RECORD
