Metadata-Version: 2.1
Name: gpgi
Version: 2.1.0
Summary: A Generic Particle+Grid Interface
Author: C.M.T. Robert
License: GPL-3.0
Classifier: Intended Audience :: Science/Research
Classifier: License :: OSI Approved :: GNU General Public License v3 (GPLv3)
Classifier: Programming Language :: Cython
Classifier: Programming Language :: Python :: 3
Classifier: Programming Language :: Python :: Free Threading :: 3 - Stable
Classifier: Typing :: Typed
Project-URL: Homepage, https://github.com/neutrinoceros/gpgi
Project-URL: Changelog, https://github.com/neutrinoceros/gpgi/blob/main/CHANGELOG.md
Requires-Python: >=3.11
Requires-Dist: numpy<3,>=1.25
